humanlayer_langgraph/__init__.py
humanlayer_langgraph/_version.py
humanlayer_langgraph/logger.py
humanlayer_langgraph/nodes.py
humanlayer_langgraph/subgraph.py
humanlayer_langgraph_alpha-0.1.0.dist-info/METADATA
humanlayer_langgraph_alpha-0.1.0.dist-info/WHEEL
humanlayer_langgraph_alpha-0.1.0.dist-info/licenses/LICENSE
humanlayer_langgraph_alpha-0.1.0.dist-info/RECORD
