Metadata-Version: 2.4
Name: humanlayer-langgraph-alpha
Version: 0.1.0
Summary: HumanLayer integration for LangGraph
Author-email: HumanLayer <info@humanlayer.com>
License: MIT License
License-File: LICENSE
Requires-Python: >=3.9
Requires-Dist: humanlayer>=0.1.0
Requires-Dist: langchain-core>=0.1.0
Requires-Dist: langchain-openai>=0.0.5
Requires-Dist: langgraph>=0.0.10
Provides-Extra: dev
Requires-Dist: black>=23.0.0; extra == 'dev'
Requires-Dist: build>=1.0.0; extra == 'dev'
Requires-Dist: bump2version>=1.0.0; extra == 'dev'
Requires-Dist: mypy>=1.0.0; extra == 'dev'
Requires-Dist: pytest>=7.0.0; extra == 'dev'
Requires-Dist: ruff>=0.0.280; extra == 'dev'
Requires-Dist: twine>=4.0.0; extra == 'dev'
